[
	{
		"race_id": 4389,
		"series_id": 1,
		"race_season": 2015,
		"race_name": "Bojangles' Southern 500",
		"race_type_id": 1,
		"restrictor_plate": false,
		"track_id": 4,
		"track_name": "Darlington Raceway",
		"date_scheduled": "2015-09-06T19:00:00",
		"race_date": "2015-09-06T19:00:00",
		"qualifying_date": "2015-09-05T00:00:00",
		"scheduled_distance": 501.32,
		"actual_distance": 501.322,
		"scheduled_laps": 367,
		"actual_laps": 367,
		"number_of_cars_in_field": 43,
		"pole_winner_driver_id": 1816,
		"pole_winner_speed": 178.874,
		"pole_winner_laptime": null,
		"number_of_lead_changes": 24,
		"number_of_leaders": 11,
		"number_of_cautions": 18,
		"number_of_caution_laps": 89,
		"average_speed": 111.993,
		"total_race_time": "04:28:35",
		"race_purse": 5762276.0,
		"race_comments": "Carl Edwards won the Bojangles' Southern 500, his 25th career NASCAR Sprint Cup Series victory and first at Darlington Raceway. Prior to the start of the race, the following cars dropped to the rear of the field for the reasons indicated: No. 10 (backup car) and No. 25 (rear gear change).",
		"attendance": 0,
		"radio_broadcaster": "MRN",
		"television_broadcaster": "NBC",
		"master_race_id": 442
	},
	{
		"race_id": 4385,
		"series_id": 1,
		"race_season": 2015,
		"race_name": "Food City 500 in Support of Steve Byrnes and Stand Up to Cancer",
		"race_type_id": 1,
		"restrictor_plate": false,
		"track_id": 14,
		"track_name": "Bristol Motor Speedway",
		"date_scheduled": "2015-04-19T13:00:00",
		"race_date": "2015-04-19T13:00:00",
		"qualifying_date": "2015-04-17T00:00:00",
		"scheduled_distance": 266.5,
		"actual_distance": 272.363,
		"scheduled_laps": 500,
		"actual_laps": 511,
		"number_of_cars_in_field": 43,
		"pole_winner_driver_id": 1810,
		"pole_winner_speed": 128.632,
		"pole_winner_laptime": null,
		"number_of_lead_changes": 21,
		"number_of_leaders": 6,
		"number_of_cautions": 11,
		"number_of_caution_laps": 117,
		"average_speed": 74.997,
		"total_race_time": "03:37:54",
		"race_purse": 5628518.0,
		"race_comments": "Matt Kenseth won the Food City 500 in Support of Steve Byrnes at Bristol Motor Speedway, his 32nd victory in the NASCAR Sprint Cup Series and fourth at the track. Prior to the start of the race, the No. 95 dropped to the rear of the field for unapproved adjustments.",
		"attendance": 0,
		"radio_broadcaster": "PRN",
		"television_broadcaster": "FOX",
		"master_race_id": 588
	},
	{
		"race_id": 4407,
		"series_id": 1,
		"race_season": 2015,
		"race_name": "IRWIN Tools Night Race",
		"race_type_id": 1,
		"restrictor_plate": false,
		"track_id": 14,
		"track_name": "Bristol Motor Speedway",
		"date_scheduled": "2015-08-22T19:30:00",
		"race_date": "2015-08-22T19:30:00",
		"qualifying_date": "2015-08-21T00:00:00",
		"scheduled_distance": 266.5,
		"actual_distance": 266.5,
		"scheduled_laps": 500,
		"actual_laps": 500,
		"number_of_cars_in_field": 43,
		"pole_winner_driver_id": 1361,
		"pole_winner_speed": 131.407,
		"pole_winner_laptime": null,
		"number_of_lead_changes": 14,
		"number_of_leaders": 5,
		"number_of_cautions": 8,
		"number_of_caution_laps": 52,
		"average_speed": 96.89,
		"total_race_time": "02:45:02",
		"race_purse": 6366322.0,
		"race_comments": "Joey Logano won the IRWIN Tools Night Race, his 11th win in the NASCAR Sprint Cup Series and his second at Bristol Motor Speedway. No cars dropped to the rear of the field prior to the start of the race.",
		"attendance": 0,
		"radio_broadcaster": "PRN",
		"television_broadcaster": "NBCSN",
		"master_race_id": 612
	},
	{
		"race_id": 4387,
		"series_id": 1,
		"race_season": 2015,
		"race_name": "STP 500",
		"race_type_id": 1,
		"restrictor_plate": false,
		"track_id": 22,
		"track_name": "Martinsville Speedway",
		"date_scheduled": "2015-03-29T13:00:00",
		"race_date": "2015-03-29T13:00:00",
		"qualifying_date": "2015-03-27T00:00:00",
		"scheduled_distance": 263.0,
		"actual_distance": 263.0,
		"scheduled_laps": 500,
		"actual_laps": 500,
		"number_of_cars_in_field": 43,
		"pole_winner_driver_id": 3859,
		"pole_winner_speed": 98.461,
		"pole_winner_laptime": null,
		"number_of_lead_changes": 31,
		"number_of_leaders": 13,
		"number_of_cautions": 16,
		"number_of_caution_laps": 112,
		"average_speed": 68.843,
		"total_race_time": "03:49:13",
		"race_purse": 5075776.0,
		"race_comments": "Denny Hamlin won the STP 500 at Martinsville Speedway, his 25th victory in the NASCAR Sprint Cup Series and fifth at the track. Prior to the start of the race, the following cars dropped to the rear of the field for the reasons indicated:  #13 (transmission), #42 (driver change) and #51 (backup car).",
		"attendance": 0,
		"radio_broadcaster": "MRN",
		"television_broadcaster": "FS1",
		"master_race_id": 12
	},
	{
		"race_id": 4416,
		"series_id": 1,
		"race_season": 2015,
		"race_name": "Goody's Headache Relief Shot 500",
		"race_type_id": 1,
		"restrictor_plate": false,
		"track_id": 22,
		"track_name": "Martinsville Speedway",
		"date_scheduled": "2015-11-01T13:15:00",
		"race_date": "2015-11-01T13:15:00",
		"qualifying_date": "2015-10-30T00:00:00",
		"scheduled_distance": 263.0,
		"actual_distance": 263.0,
		"scheduled_laps": 500,
		"actual_laps": 500,
		"number_of_cars_in_field": 43,
		"pole_winner_driver_id": 3859,
		"pole_winner_speed": 98.548,
		"pole_winner_laptime": null,
		"number_of_lead_changes": 21,
		"number_of_leaders": 9,
		"number_of_cautions": 18,
		"number_of_caution_laps": 109,
		"average_speed": 69.643,
		"total_race_time": "03:46:35",
		"race_purse": 5202126.0,
		"race_comments": "Jeff Gordon won the Goody's Headache Relief Shot 500, his 93rd career NASCAR Sprint Cup Series victory and ninth at Martinsville Speedway. Prior to the start of the race, the following cars dropped to the rear of the field for the reasons indicated: No. 5 and No. 14 (backup car).",
		"attendance": 0,
		"radio_broadcaster": "MRN",
		"television_broadcaster": "NBCSN",
		"master_race_id": 6
	},
	{
		"race_id": 4390,
		"series_id": 1,
		"race_season": 2015,
		"race_name": "Toyota Owners 400 ",
		"race_type_id": 1,
		"restrictor_plate": false,
		"track_id": 26,
		"track_name": "Richmond International Raceway",
		"date_scheduled": "2015-04-25T19:00:00",
		"race_date": "2015-04-26T00:00:00",
		"qualifying_date": "2015-04-24T00:00:00",
		"scheduled_distance": 300.0,
		"actual_distance": 300.0,
		"scheduled_laps": 400,
		"actual_laps": 400,
		"number_of_cars_in_field": 43,
		"pole_winner_driver_id": 3859,
		"pole_winner_speed": 127.071,
		"pole_winner_laptime": null,
		"number_of_lead_changes": 12,
		"number_of_leaders": 5,
		"number_of_cautions": 8,
		"number_of_caution_laps": 53,
		"average_speed": 97.157,
		"total_race_time": "03:05:16",
		"race_purse": 5171635.0,
		"race_comments": "Kurt Busch won the Toyota Owners 400 at Richmond International Raceway, his 26th victory in the NASCAR Sprint Cup Series and second at the track. Prior to the start of the race, the following cars dropped to the rear of the field for the reasons indicated: #23 (driver change), #35 (transmission change), #30 (engine change).",
		"attendance": 0,
		"radio_broadcaster": "MRN",
		"television_broadcaster": "FOX",
		"master_race_id": 1555
	},
	{
		"race_id": 4409,
		"series_id": 1,
		"race_season": 2015,
		"race_name": "Federated Auto Parts 400",
		"race_type_id": 1,
		"restrictor_plate": false,
		"track_id": 26,
		"track_name": "Richmond International Raceway",
		"date_scheduled": "2015-09-12T19:30:00",
		"race_date": "2015-09-12T19:30:00",
		"qualifying_date": "2015-09-11T00:00:00",
		"scheduled_distance": 300.0,
		"actual_distance": 300.0,
		"scheduled_laps": 400,
		"actual_laps": 400,
		"number_of_cars_in_field": 43,
		"pole_winner_driver_id": 3859,
		"pole_winner_speed": 126.47,
		"pole_winner_laptime": null,
		"number_of_lead_changes": 13,
		"number_of_leaders": 4,
		"number_of_cautions": 6,
		"number_of_caution_laps": 47,
		"average_speed": 100.353,
		"total_race_time": "02:59:22",
		"race_purse": 5202126.0,
		"race_comments": "Matt Kenseth won the Federated Auto Parts 400, his 35th career NASCAR Sprint Cup Series victory.",
		"attendance": 0,
		"radio_broadcaster": "MRN",
		"television_broadcaster": "NBCSN",
		"master_race_id": 1544
	},
	{
		"race_id": 4386,
		"series_id": 1,
		"race_season": 2015,
		"race_name": "Auto Club 400",
		"race_type_id": 1,
		"restrictor_plate": false,
		"track_id": 38,
		"track_name": "Auto Club Speedway",
		"date_scheduled": "2015-03-22T15:30:00",
		"race_date": "2015-03-22T15:30:00",
		"qualifying_date": "2015-03-20T00:00:00",
		"scheduled_distance": 400.0,
		"actual_distance": 418.0,
		"scheduled_laps": 200,
		"actual_laps": 209,
		"number_of_cars_in_field": 43,
		"pole_winner_driver_id": 453,
		"pole_winner_speed": 185.142,
		"pole_winner_laptime": null,
		"number_of_lead_changes": 19,
		"number_of_leaders": 9,
		"number_of_cautions": 7,
		"number_of_caution_laps": 31,
		"average_speed": 140.662,
		"total_race_time": "02:58:18",
		"race_purse": 5950387.0,
		"race_comments": "Brad Keselowski won the Auto Club 400 at Auto Club Speedway, his 17th victory in the NASCAR Sprint Cup Series and first at the track. Prior to the start of the race, the following car dropped to the rear of the field for the reason indicated:  #55 (backup car).",
		"attendance": 0,
		"radio_broadcaster": "MRN",
		"television_broadcaster": "FOX",
		"master_race_id": 1804
	},
	{
		"race_id": 4410,
		"series_id": 1,
		"race_season": 2015,
		"race_name": "myAFibRisk.com 400",
		"race_type_id": 1,
		"restrictor_plate": false,
		"track_id": 39,
		"track_name": "Chicagoland Speedway",
		"date_scheduled": "2015-09-20T15:00:00",
		"race_date": "2015-09-20T15:00:00",
		"qualifying_date": "1900-01-01T00:00:00",
		"scheduled_distance": 400.5,
		"actual_distance": 400.5,
		"scheduled_laps": 267,
		"actual_laps": 267,
		"number_of_cars_in_field": 43,
		"pole_winner_driver_id": 0,
		"pole_winner_speed": 0.0,
		"pole_winner_laptime": null,
		"number_of_lead_changes": 17,
		"number_of_leaders": 10,
		"number_of_cautions": 6,
		"number_of_caution_laps": 28,
		"average_speed": 140.117,
		"total_race_time": "02:51:30",
		"race_purse": 6144256.0,
		"race_comments": "Denny Hamlin won the myAFibRisk.com 400, his 26th career NASCAR Sprint Cup Series victory. Prior to the start of the race, the following car dropped to the rear of the field for the reasons indicated: No. 34 (transmission change).",
		"attendance": 0,
		"radio_broadcaster": "MRN",
		"television_broadcaster": "NBCSN",
		"master_race_id": 1976
	},
	{
		"race_id": 4419,
		"series_id": 1,
		"race_season": 2015,
		"race_name": "Ford EcoBoost 400",
		"race_type_id": 1,
		"restrictor_plate": false,
		"track_id": 40,
		"track_name": "Homestead-Miami Speedway",
		"date_scheduled": "2015-11-22T15:00:00",
		"race_date": "2015-11-22T15:00:00",
		"qualifying_date": "2015-11-20T00:00:00",
		"scheduled_distance": 400.5,
		"actual_distance": 400.5,
		"scheduled_laps": 267,
		"actual_laps": 267,
		"number_of_cars_in_field": 43,
		"pole_winner_driver_id": 1361,
		"pole_winner_speed": 176.655,
		"pole_winner_laptime": null,
		"number_of_lead_changes": 18,
		"number_of_leaders": 8,
		"number_of_cautions": 7,
		"number_of_caution_laps": 30,
		"average_speed": 131.755,
		"total_race_time": "03:02:23",
		"race_purse": 5378116.0,
		"race_comments": "Kyle Busch won the Ford EcoBoost 400, his 34th career NASCAR Sprint Cup Series victory. Prior to the start of the race, the following cars \n\ndropped to the rear of the field for the reason indicated: No. 38 (transmission change).",
		"attendance": 0,
		"radio_broadcaster": "MRN",
		"television_broadcaster": "NBC",
		"master_race_id": 1887
	},
	{
		"race_id": 4392,
		"series_id": 1,
		"race_season": 2015,
		"race_name": "SpongeBob SquarePants 400",
		"race_type_id": 1,
		"restrictor_plate": false,
		"track_id": 41,
		"track_name": "Kansas Speedway",
		"date_scheduled": "2015-05-09T19:30:00",
		"race_date": "2015-05-09T19:30:00",
		"qualifying_date": "2015-05-08T00:00:00",
		"scheduled_distance": 400.5,
		"actual_distance": 400.5,
		"scheduled_laps": 267,
		"actual_laps": 267,
		"number_of_cars_in_field": 43,
		"pole_winner_driver_id": 3859,
		"pole_winner_speed": 192.397,
		"pole_winner_laptime": null,
		"number_of_lead_changes": 16,
		"number_of_leaders": 10,
		"number_of_cautions": 9,
		"number_of_caution_laps": 49,
		"average_speed": 125.265,
		"total_race_time": "03:11:50",
		"race_purse": 5400236.0,
		"race_comments": "Jimmie Johnson won the SpongeBob SquarePants 400, his 73rd victory in the NASCAR Sprint Cup Series and third at the track. Prior to the start of the race, no cars dropped to the rear of the field.",
		"attendance": 0,
		"radio_broadcaster": "MRN",
		"television_broadcaster": "FS1",
		"master_race_id": 3884
	},
	{
		"race_id": 4413,
		"series_id": 1,
		"race_season": 2015,
		"race_name": "Hollywood Casino 400",
		"race_type_id": 1,
		"restrictor_plate": false,
		"track_id": 41,
		"track_name": "Kansas Speedway",
		"date_scheduled": "2015-10-18T14:15:00",
		"race_date": "2015-10-18T14:15:00",
		"qualifying_date": "2015-10-16T00:00:00",
		"scheduled_distance": 400.0,
		"actual_distance": 403.5,
		"scheduled_laps": 267,
		"actual_laps": 269,
		"number_of_cars_in_field": 43,
		"pole_winner_driver_id": 1816,
		"pole_winner_speed": 195.503,
		"pole_winner_laptime": null,
		"number_of_lead_changes": 21,
		"number_of_leaders": 9,
		"number_of_cautions": 7,
		"number_of_caution_laps": 39,
		"average_speed": 135.732,
		"total_race_time": "02:58:22",
		"race_purse": 6144256.0,
		"race_comments": "Joey Logano won the Hollywood Casino 400, his 13th career NASCAR Sprint Cup Series victory. Prior to the start of the race, the following cars dropped to the rear of the field for the reasons indicated: No. 13 (backup car).",
		"attendance": 0,
		"radio_broadcaster": "MRN",
		"television_broadcaster": "NBC",
		"master_race_id": 1950
	},
	{
		"race_id": 4384,
		"series_id": 1,
		"race_season": 2015,
		"race_name": "Kobalt 400",
		"race_type_id": 1,
		"restrictor_plate": false,
		"track_id": 42,
		"track_name": "Las Vegas Motor Speedway",
		"date_scheduled": "2015-03-08T15:30:00",
		"race_date": "2015-03-08T15:30:00",
		"qualifying_date": "2015-03-06T00:00:00",
		"scheduled_distance": 400.5,
		"actual_distance": 400.5,
		"scheduled_laps": 267,
		"actual_laps": 267,
		"number_of_cars_in_field": 43,
		"pole_winner_driver_id": 1237,
		"pole_winner_speed": 194.679,
		"pole_winner_laptime": null,
		"number_of_lead_changes": 19,
		"number_of_leaders": 10,
		"number_of_cautions": 6,
		"number_of_caution_laps": 28,
		"average_speed": 143.677,
		"total_race_time": "02:47:15",
		"race_purse": 6495939.0,
		"race_comments": "Kevin Harvick won the Kobalt 400 at Las Vegas Motor Speedway, his 29th victory in the NASCAR Sprint Cup Series. Prior to the start of the race, the following cars dropped to the rear of the field for the reasons indicated: #18, 24 (backup car).",
		"attendance": 0,
		"radio_broadcaster": "PRN",
		"television_broadcaster": "FOX",
		"master_race_id": 1824
	},
	{
		"race_id": 4388,
		"series_id": 1,
		"race_season": 2015,
		"race_name": "Duck Commander 500",
		"race_type_id": 1,
		"restrictor_plate": false,
		"track_id": 43,
		"track_name": "Texas Motor Speedway",
		"date_scheduled": "2015-04-11T19:30:00",
		"race_date": "2015-04-11T19:30:00",
		"qualifying_date": "2015-04-10T00:00:00",
		"scheduled_distance": 501.0,
		"actual_distance": 501.0,
		"scheduled_laps": 334,
		"actual_laps": 334,
		"number_of_cars_in_field": 43,
		"pole_winner_driver_id": 453,
		"pole_winner_speed": 193.847,
		"pole_winner_laptime": null,
		"number_of_lead_changes": 29,
		"number_of_leaders": 9,
		"number_of_cautions": 8,
		"number_of_caution_laps": 40,
		"average_speed": 140.5,
		"total_race_time": "03:33:57",
		"race_purse": 7260922.0,
		"race_comments": "Jimmie Johnson won the Duck Commander 500 at Texas Motor Speedway, his 72nd victory in the NASCAR Sprint Cup Series. Prior to the start of the race, the following car dropped to the rear of the field for the reason indicated:  #31 (engine change).",
		"attendance": 0,
		"radio_broadcaster": "PRN",
		"television_broadcaster": "FOX",
		"master_race_id": 1795
	},
	{
		"race_id": 4417,
		"series_id": 1,
		"race_season": 2015,
		"race_name": "AAA Texas 500",
		"race_type_id": 1,
		"restrictor_plate": false,
		"track_id": 43,
		"track_name": "Texas Motor Speedway",
		"date_scheduled": "2015-11-08T14:00:00",
		"race_date": "2015-11-08T14:00:00",
		"qualifying_date": "2015-11-06T00:00:00",
		"scheduled_distance": 501.0,
		"actual_distance": 501.0,
		"scheduled_laps": 334,
		"actual_laps": 334,
		"number_of_cars_in_field": 43,
		"pole_winner_driver_id": 1816,
		"pole_winner_speed": 196.929,
		"pole_winner_laptime": null,
		"number_of_lead_changes": 15,
		"number_of_leaders": 8,
		"number_of_cautions": 9,
		"number_of_caution_laps": 47,
		"average_speed": 137.49,
		"total_race_time": "03:38:38",
		"race_purse": 7075075.0,
		"race_comments": "Jimmie Johnson won the AAA Texas 500, his 75th career NASCAR Sprint Cup Series victory. Prior to the start of the race, the following cars dropped to the rear of the field for the reasons indicated: Nos. 98 (engine change) and 14 (missed driver introductions).",
		"attendance": 0,
		"radio_broadcaster": "PRN",
		"television_broadcaster": "NBC",
		"master_race_id": 2100
	},
	{
		"race_id": 4400,
		"series_id": 1,
		"race_season": 2015,
		"race_name": "Quaker State 400 Presented by Advance Auto Parts",
		"race_type_id": 1,
		"restrictor_plate": false,
		"track_id": 61,
		"track_name": "Kentucky Speedway",
		"date_scheduled": "2015-07-11T19:30:00",
		"race_date": "2015-07-11T19:30:00",
		"qualifying_date": "2015-07-10T00:00:00",
		"scheduled_distance": 400.5,
		"actual_distance": 400.5,
		"scheduled_laps": 267,
		"actual_laps": 267,
		"number_of_cars_in_field": 43,
		"pole_winner_driver_id": 0,
		"pole_winner_speed": 0.0,
		"pole_winner_laptime": null,
		"number_of_lead_changes": 13,
		"number_of_leaders": 8,
		"number_of_cautions": 11,
		"number_of_caution_laps": 49,
		"average_speed": 129.402,
		"total_race_time": "03:05:42",
		"race_purse": 5104114.0,
		"race_comments": "Kyle Busch won the Quaker State 400 presented by Advance Auto Parts, his 31st career NASCAR Sprint Cup Series victory. Prior to the start of the race, \r\nno cars dropped to the rear of the field.",
		"attendance": 0,
		"radio_broadcaster": "PRN",
		"television_broadcaster": "NBCSN",
		"master_race_id": 3889
	},
	{
		"race_id": 4391,
		"series_id": 1,
		"race_season": 2015,
		"race_name": "GEICO 500",
		"race_type_id": 1,
		"restrictor_plate": true,
		"track_id": 82,
		"track_name": "Talladega Superspeedway",
		"date_scheduled": "2015-05-03T13:00:00",
		"race_date": "2015-05-03T13:00:00",
		"qualifying_date": "2015-05-02T00:00:00",
		"scheduled_distance": 500.0,
		"actual_distance": 500.08,
		"scheduled_laps": 188,
		"actual_laps": 188,
		"number_of_cars_in_field": 43,
		"pole_winner_driver_id": 1237,
		"pole_winner_speed": 194.793,
		"pole_winner_laptime": null,
		"number_of_lead_changes": 27,
		"number_of_leaders": 15,
		"number_of_cautions": 6,
		"number_of_caution_laps": 23,
		"average_speed": 159.487,
		"total_race_time": "03:08:08",
		"race_purse": 6183287.0,
		"race_comments": "Dale Earnhardt Jr. won the GEICO 500 at Talladega Superspeedway, his 24th victory in the NASCAR Sprint Cup Series. Prior to the start of the race, no cars dropped to the rear of the field.",
		"attendance": 0,
		"radio_broadcaster": "MRN",
		"television_broadcaster": "FOX",
		"master_race_id": 957
	},
	{
		"race_id": 4415,
		"series_id": 1,
		"race_season": 2015,
		"race_name": "CampingWorld.com 500 at Talladega",
		"race_type_id": 1,
		"restrictor_plate": true,
		"track_id": 82,
		"track_name": "Talladega Superspeedway",
		"date_scheduled": "2015-10-25T14:30:00",
		"race_date": "2015-10-25T14:30:00",
		"qualifying_date": "2015-10-24T00:00:00",
		"scheduled_distance": 500.0,
		"actual_distance": 521.36,
		"scheduled_laps": 188,
		"actual_laps": 196,
		"number_of_cars_in_field": 43,
		"pole_winner_driver_id": 1237,
		"pole_winner_speed": 194.5,
		"pole_winner_laptime": null,
		"number_of_lead_changes": 30,
		"number_of_leaders": 18,
		"number_of_cautions": 3,
		"number_of_caution_laps": 18,
		"average_speed": 167.311,
		"total_race_time": "03:06:58",
		"race_purse": 5446886.0,
		"race_comments": "Joey Logano won the CampingWorld.com 500, his 14th career NASCAR Sprint Cup Series victory. Prior to the start of the race, the following cars dropped to the rear of the field for the reasons indicated: No. 10 (transmission repair), No. 14 (unapproved adjustments) and No. 51 (repairs).",
		"attendance": 0,
		"radio_broadcaster": "MRN",
		"television_broadcaster": "NBCSN",
		"master_race_id": 937
	},
	{
		"race_id": 4383,
		"series_id": 1,
		"race_season": 2015,
		"race_name": "CampingWorld.com 500",
		"race_type_id": 1,
		"restrictor_plate": false,
		"track_id": 84,
		"track_name": "Phoenix International Raceway",
		"date_scheduled": "2015-03-15T15:30:00",
		"race_date": "2015-03-15T15:30:00",
		"qualifying_date": "2015-03-13T00:00:00",
		"scheduled_distance": 312.0,
		"actual_distance": 312.0,
		"scheduled_laps": 312,
		"actual_laps": 312,
		"number_of_cars_in_field": 43,
		"pole_winner_driver_id": 1416,
		"pole_winner_speed": 140.751,
		"pole_winner_laptime": null,
		"number_of_lead_changes": 8,
		"number_of_leaders": 4,
		"number_of_cautions": 10,
		"number_of_caution_laps": 53,
		"average_speed": 105.753,
		"total_race_time": "02:57:01",
		"race_purse": 5107970.0,
		"race_comments": "Kevin Harvick won the CampingWorld.com 500 at Phoenix International Raceway, his 30th victory in the NASCAR Sprint Cup Series and seventh at Phoenix. Prior to the start of the race, the following cars dropped to the rear of the field for the reasons indicated:  #47 (engine change).",
		"attendance": 0,
		"radio_broadcaster": "MRN",
		"television_broadcaster": "FOX",
		"master_race_id": 2074
	},
	{
		"race_id": 4418,
		"series_id": 1,
		"race_season": 2015,
		"race_name": "Quicken Loans Race for Heroes 500",
		"race_type_id": 1,
		"restrictor_plate": false,
		"track_id": 84,
		"track_name": "Phoenix International Raceway",
		"date_scheduled": "2015-11-15T14:30:00",
		"race_date": "2015-11-15T14:30:00",
		"qualifying_date": "2015-11-13T00:00:00",
		"scheduled_distance": 312.0,
		"actual_distance": 219.0,
		"scheduled_laps": 312,
		"actual_laps": 219,
		"number_of_cars_in_field": 43,
		"pole_winner_driver_id": 1717,
		"pole_winner_speed": 143.158,
		"pole_winner_laptime": null,
		"number_of_lead_changes": 8,
		"number_of_leaders": 7,
		"number_of_cautions": 2,
		"number_of_caution_laps": 29,
		"average_speed": 106.512,
		"total_race_time": "02:03:22",
		"race_purse": 5202126.0,
		"race_comments": "Dale Earnhardt Jr. won the Quicken Loans Race for Heroes 500, his 26th career NASCAR Sprint Cup Series victory.",
		"attendance": 0,
		"radio_broadcaster": "MRN",
		"television_broadcaster": "NBCSN",
		"master_race_id": 1550
	},
	{
		"race_id": 4399,
		"series_id": 1,
		"race_season": 2015,
		"race_name": "Toyota - Save Mart 350",
		"race_type_id": 1,
		"restrictor_plate": false,
		"track_id": 99,
		"track_name": "Sonoma Raceway",
		"date_scheduled": "2015-06-28T15:00:00",
		"race_date": "2015-06-28T15:00:00",
		"qualifying_date": "2015-06-27T00:00:00",
		"scheduled_distance": 218.9,
		"actual_distance": 218.9,
		"scheduled_laps": 110,
		"actual_laps": 110,
		"number_of_cars_in_field": 43,
		"pole_winner_driver_id": 3774,
		"pole_winner_speed": 96.31,
		"pole_winner_laptime": null,
		"number_of_lead_changes": 9,
		"number_of_leaders": 5,
		"number_of_cautions": 5,
		"number_of_caution_laps": 21,
		"average_speed": 74.774,
		"total_race_time": "02:55:39",
		"race_purse": 5735702.0,
		"race_comments": "Kyle Busch won the Toyota/Save Mart 350, his 30th career NASCAR Sprint Series victory. Prior to the start of the race, the following cars dropped to the rear of the field for the reasons indicated: Nos. 27, 46 (engine change).",
		"attendance": 0,
		"radio_broadcaster": "PRN",
		"television_broadcaster": "FS1",
		"master_race_id": 1563
	},
	{
		"race_id": 4396,
		"series_id": 1,
		"race_season": 2015,
		"race_name": "FedEx 400 Benefiting Autism Speaks",
		"race_type_id": 1,
		"restrictor_plate": false,
		"track_id": 103,
		"track_name": "Dover International Speedway",
		"date_scheduled": "2015-05-31T13:00:00",
		"race_date": "2015-05-31T13:00:00",
		"qualifying_date": "2015-05-29T00:00:00",
		"scheduled_distance": 400.0,
		"actual_distance": 405.0,
		"scheduled_laps": 400,
		"actual_laps": 405,
		"number_of_cars_in_field": 43,
		"pole_winner_driver_id": 1361,
		"pole_winner_speed": 160.121,
		"pole_winner_laptime": null,
		"number_of_lead_changes": 15,
		"number_of_leaders": 9,
		"number_of_cautions": 7,
		"number_of_caution_laps": 40,
		"average_speed": 119.547,
		"total_race_time": "03:23:16",
		"race_purse": 5977115.0,
		"race_comments": "Jimmie Johnson won the FedEx 400 benefiting Autism Speaks, his 74th career NASCAR Sprint Series victory. Prior to the start of the race, the following cars dropped to the rear of the field for the reason indicated: No. 88 (changing rear gear).",
		"attendance": 0,
		"radio_broadcaster": "MRN",
		"television_broadcaster": "FS1",
		"master_race_id": 922
	},
	{
		"race_id": 4412,
		"series_id": 1,
		"race_season": 2015,
		"race_name": "AAA 400",
		"race_type_id": 1,
		"restrictor_plate": false,
		"track_id": 103,
		"track_name": "Dover International Speedway",
		"date_scheduled": "2015-10-04T14:30:00",
		"race_date": "2015-10-04T14:30:00",
		"qualifying_date": "1900-01-01T00:00:00",
		"scheduled_distance": 400.0,
		"actual_distance": 400.0,
		"scheduled_laps": 400,
		"actual_laps": 400,
		"number_of_cars_in_field": 43,
		"pole_winner_driver_id": 0,
		"pole_winner_speed": 0.0,
		"pole_winner_laptime": null,
		"number_of_lead_changes": 14,
		"number_of_leaders": 3,
		"number_of_cautions": 8,
		"number_of_caution_laps": 43,
		"average_speed": 119.87,
		"total_race_time": "03:20:13",
		"race_purse": 5255734.0,
		"race_comments": "Kevin Harvick won the AAA 400, his 31st career NASCAR Sprint Cup Series victory. Prior to the start of the race, the following car dropped to the rear of the field for the reason indicated: No. 78 (unapproved adjustments).",
		"attendance": 0,
		"radio_broadcaster": "MRN",
		"television_broadcaster": "NBCSN",
		"master_race_id": 1038
	},
	{
		"race_id": 4379,
		"series_id": 1,
		"race_season": 2015,
		"race_name": "Sprint Unlimited",
		"race_type_id": 2,
		"restrictor_plate": true,
		"track_id": 105,
		"track_name": "Daytona International Speedway",
		"date_scheduled": "2015-02-14T20:00:00",
		"race_date": "2015-02-14T20:00:00",
		"qualifying_date": "1900-01-01T00:00:00",
		"scheduled_distance": 187.5,
		"actual_distance": 187.5,
		"scheduled_laps": 75,
		"actual_laps": 75,
		"number_of_cars_in_field": 25,
		"pole_winner_driver_id": 0,
		"pole_winner_speed": 0.0,
		"pole_winner_laptime": null,
		"number_of_lead_changes": 13,
		"number_of_leaders": 8,
		"number_of_cautions": 4,
		"number_of_caution_laps": 17,
		"average_speed": 135.569,
		"total_race_time": "01:22:59",
		"race_purse": 1051074.0,
		"race_comments": "Matt Kenseth won the Sprint Unlimited at Daytona International Speedway, his first victory in the preseason event. Prior to the start of the race, no cars dropped to the rear under penalty.",
		"attendance": 0,
		"radio_broadcaster": "MRN",
		"television_broadcaster": "FOX",
		"master_race_id": 3222
	},
	{
		"race_id": 4380,
		"series_id": 1,
		"race_season": 2015,
		"race_name": "Budweiser Duel #1",
		"race_type_id": 2,
		"restrictor_plate": true,
		"track_id": 105,
		"track_name": "Daytona International Speedway",
		"date_scheduled": "2015-02-19T19:00:00",
		"race_date": "2015-02-19T19:00:00",
		"qualifying_date": "1900-01-01T00:00:00",
		"scheduled_distance": 150.0,
		"actual_distance": 150.0,
		"scheduled_laps": 60,
		"actual_laps": 60,
		"number_of_cars_in_field": 25,
		"pole_winner_driver_id": 0,
		"pole_winner_speed": 0.0,
		"pole_winner_laptime": null,
		"number_of_lead_changes": 9,
		"number_of_leaders": 5,
		"number_of_cautions": 3,
		"number_of_caution_laps": 13,
		"average_speed": 144.462,
		"total_race_time": "01:02:18",
		"race_purse": 19809272.0,
		"race_comments": "Dale Earnhardt Jr. won the Budweiser Duel at Daytona #1 at Daytona International Speedway, his fourth victory in the Daytona 500 qualifying event. Prior to the start of the race, the following cars dropped to the rear of the field: #15, 23, 46 (backup car), 88 (failed post qualifying inspection).",
		"attendance": 0,
		"radio_broadcaster": "MRN",
		"television_broadcaster": "FS1",
		"master_race_id": 3217
	},
	{
		"race_id": 4381,
		"series_id": 1,
		"race_season": 2015,
		"race_name": "Budweiser Duel #2 ",
		"race_type_id": 2,
		"restrictor_plate": true,
		"track_id": 105,
		"track_name": "Daytona International Speedway",
		"date_scheduled": "2015-02-19T19:00:00",
		"race_date": "2015-02-19T19:00:00",
		"qualifying_date": "1900-01-01T00:00:00",
		"scheduled_distance": 150.0,
		"actual_distance": 160.0,
		"scheduled_laps": 60,
		"actual_laps": 64,
		"number_of_cars_in_field": 24,
		"pole_winner_driver_id": 0,
		"pole_winner_speed": 0.0,
		"pole_winner_laptime": null,
		"number_of_lead_changes": 7,
		"number_of_leaders": 5,
		"number_of_cautions": 3,
		"number_of_caution_laps": 12,
		"average_speed": 144.724,
		"total_race_time": "01:06:20",
		"race_purse": 19809272.0,
		"race_comments": "Jimmie Johnson won the Budweiser Duel at Daytona #2 at Daytona International Speedway, his second victory in the Daytona 500 qualifying event. Prior to the start of the race, the following cars dropped to the rear of the field: #31 (engine change) #32, 10, 26, 44 (backup car), 11 (failed post qualifying inspection).",
		"attendance": 0,
		"radio_broadcaster": "MRN",
		"television_broadcaster": "FS1",
		"master_race_id": 3218
	},
	{
		"race_id": 4382,
		"series_id": 1,
		"race_season": 2015,
		"race_name": "Daytona 500",
		"race_type_id": 1,
		"restrictor_plate": true,
		"track_id": 105,
		"track_name": "Daytona International Speedway",
		"date_scheduled": "2015-02-22T13:00:00",
		"race_date": "2015-02-22T13:00:00",
		"qualifying_date": "2015-02-15T00:00:00",
		"scheduled_distance": 500.0,
		"actual_distance": 507.5,
		"scheduled_laps": 200,
		"actual_laps": 203,
		"number_of_cars_in_field": 43,
		"pole_winner_driver_id": 1237,
		"pole_winner_speed": 201.293,
		"pole_winner_laptime": null,
		"number_of_lead_changes": 27,
		"number_of_leaders": 12,
		"number_of_cautions": 7,
		"number_of_caution_laps": 26,
		"average_speed": 161.939,
		"total_race_time": "03:08:02",
		"race_purse": 19809272.0,
		"race_comments": "Joey Logano won the Daytona 500 at Daytona International Speedway, his ninth victory in the NASCAR Sprint Cup Series and first Daytona 500. Prior to the start of the race, the following cars dropped to the rear of the field for the reason indicated: #18, #41 (Driver Change), #3, #6, #9, #10, #31, #32, #34, #42, #47, #83 (Backup Car).",
		"attendance": 0,
		"radio_broadcaster": "MRN",
		"television_broadcaster": "FOX",
		"master_race_id": 385
	},
	{
		"race_id": 4401,
		"series_id": 1,
		"race_season": 2015,
		"race_name": "Coke Zero 400 Powered by Coca-Cola",
		"race_type_id": 1,
		"restrictor_plate": true,
		"track_id": 105,
		"track_name": "Daytona International Speedway",
		"date_scheduled": "2015-07-05T19:45:00",
		"race_date": "2015-07-05T19:45:00",
		"qualifying_date": "2015-07-04T00:00:00",
		"scheduled_distance": 400.0,
		"actual_distance": 402.5,
		"scheduled_laps": 160,
		"actual_laps": 161,
		"number_of_cars_in_field": 43,
		"pole_winner_driver_id": 0,
		"pole_winner_speed": 0.0,
		"pole_winner_laptime": null,
		"number_of_lead_changes": 22,
		"number_of_leaders": 12,
		"number_of_cautions": 9,
		"number_of_caution_laps": 43,
		"average_speed": 134.941,
		"total_race_time": "02:58:58",
		"race_purse": 6343472.0,
		"race_comments": "Dale Earnhardt Jr. won the Coke Zero 400, his 25th career NASCAR Sprint Cup Series victory. Prior to the start of the race, no cars dropped to the rear of the field.",
		"attendance": 0,
		"radio_broadcaster": "MRN",
		"television_broadcaster": "NBC",
		"master_race_id": 408
	},
	{
		"race_id": 4408,
		"series_id": 1,
		"race_season": 2015,
		"race_name": "Folds of Honor QuikTrip 500",
		"race_type_id": 1,
		"restrictor_plate": false,
		"track_id": 111,
		"track_name": "Atlanta Motor Speedway",
		"date_scheduled": "2015-03-01T13:00:00",
		"race_date": "2015-03-01T13:00:00",
		"qualifying_date": "2015-02-27T00:00:00",
		"scheduled_distance": 500.5,
		"actual_distance": 500.5,
		"scheduled_laps": 325,
		"actual_laps": 325,
		"number_of_cars_in_field": 43,
		"pole_winner_driver_id": 3859,
		"pole_winner_speed": 194.683,
		"pole_winner_laptime": null,
		"number_of_lead_changes": 28,
		"number_of_leaders": 12,
		"number_of_cautions": 10,
		"number_of_caution_laps": 54,
		"average_speed": 131.078,
		"total_race_time": "03:49:06",
		"race_purse": 6299292.0,
		"race_comments": "Jimmie Johnson won the Folds of Honor QuikTrip 500 at Atlanta Motor Speedway, his 71st victory in the NASCAR Sprint Cup Series and fourth at Atlanta. Prior to the start of the race, the following cars dropped to the rear of the field for the reasons indicated: #4 (engine change), #14 (missed driver introductions), #33 (driver change).",
		"attendance": 0,
		"radio_broadcaster": "PRN",
		"television_broadcaster": "FOX",
		"master_race_id": 3335
	},
	{
		"race_id": 4403,
		"series_id": 1,
		"race_season": 2015,
		"race_name": "Crown Royal Presents the Jeff Kyle 400 at the Brickyard",
		"race_type_id": 1,
		"restrictor_plate": false,
		"track_id": 123,
		"track_name": "Indianapolis Motor Speedway",
		"date_scheduled": "2015-07-26T15:30:00",
		"race_date": "2015-07-26T15:30:00",
		"qualifying_date": "2015-07-25T00:00:00",
		"scheduled_distance": 400.0,
		"actual_distance": 410.0,
		"scheduled_laps": 160,
		"actual_laps": 164,
		"number_of_cars_in_field": 43,
		"pole_winner_driver_id": 923,
		"pole_winner_speed": 183.464,
		"pole_winner_laptime": null,
		"number_of_lead_changes": 16,
		"number_of_leaders": 6,
		"number_of_cautions": 9,
		"number_of_caution_laps": 36,
		"average_speed": 131.656,
		"total_race_time": "03:06:51",
		"race_purse": 9358657.0,
		"race_comments": "Kyle Busch won the Crown Royal Presents the Jeff Kyle 400 at the Brickyard, his 33rd career NASCAR Sprint Cup Series victory. Prior to the \n\nstart of the race, no cars dropped to the rear of the field.",
		"attendance": 0,
		"radio_broadcaster": "IMS",
		"television_broadcaster": "NBCSN",
		"master_race_id": 1716
	},
	{
		"race_id": 4398,
		"series_id": 1,
		"race_season": 2015,
		"race_name": "Quicken Loans 400",
		"race_type_id": 1,
		"restrictor_plate": false,
		"track_id": 133,
		"track_name": "Michigan International Speedway",
		"date_scheduled": "2015-06-14T13:00:00",
		"race_date": "2015-06-14T13:00:00",
		"qualifying_date": "2015-06-12T00:00:00",
		"scheduled_distance": 400.0,
		"actual_distance": 276.0,
		"scheduled_laps": 200,
		"actual_laps": 138,
		"number_of_cars_in_field": 43,
		"pole_winner_driver_id": 1772,
		"pole_winner_speed": 201.992,
		"pole_winner_laptime": null,
		"number_of_lead_changes": 17,
		"number_of_leaders": 11,
		"number_of_cautions": 5,
		"number_of_caution_laps": 38,
		"average_speed": 116.688,
		"total_race_time": "02:21:55",
		"race_purse": 5263885.0,
		"race_comments": "Kurt Busch won the Quicken Loans 400, his 27th career NASCAR Sprint Series victory. The race was shortened due to inclement weather. Prior to the start \r\nof the race, the following car dropped to the rear of the field for the reason indicated: No. 23 (engine change).",
		"attendance": 0,
		"radio_broadcaster": "MRN",
		"television_broadcaster": "FS1",
		"master_race_id": 917
	},
	{
		"race_id": 4406,
		"series_id": 1,
		"race_season": 2015,
		"race_name": "Pure Michigan 400",
		"race_type_id": 1,
		"restrictor_plate": false,
		"track_id": 133,
		"track_name": "Michigan International Speedway",
		"date_scheduled": "2015-08-16T14:30:00",
		"race_date": "2015-08-16T14:30:00",
		"qualifying_date": "2015-08-14T00:00:00",
		"scheduled_distance": 400.0,
		"actual_distance": 400.0,
		"scheduled_laps": 200,
		"actual_laps": 200,
		"number_of_cars_in_field": 43,
		"pole_winner_driver_id": 1810,
		"pole_winner_speed": 197.488,
		"pole_winner_laptime": null,
		"number_of_lead_changes": 16,
		"number_of_leaders": 8,
		"number_of_cautions": 8,
		"number_of_caution_laps": 31,
		"average_speed": 143.455,
		"total_race_time": "02:47:18",
		"race_purse": 5260905.0,
		"race_comments": "Matt Kenseth won the Pure Michigan 400, his 34th career NASCAR Sprint Cup Series victory. Prior to the start of the race, the following cars dropped to the rear of the field for the reasons indicated: Nos. 3, 33 (engine change); No. 18 (backup car).",
		"attendance": 0,
		"radio_broadcaster": "MRN",
		"television_broadcaster": "NBCSN",
		"master_race_id": 930
	},
	{
		"race_id": 4402,
		"series_id": 1,
		"race_season": 2015,
		"race_name": "5-hour ENERGY 301",
		"race_type_id": 1,
		"restrictor_plate": false,
		"track_id": 138,
		"track_name": "New Hampshire Motor Speedway",
		"date_scheduled": "2015-07-19T13:30:00",
		"race_date": "2015-07-19T13:30:00",
		"qualifying_date": "2015-07-17T00:00:00",
		"scheduled_distance": 318.46,
		"actual_distance": 318.458,
		"scheduled_laps": 301,
		"actual_laps": 301,
		"number_of_cars_in_field": 43,
		"pole_winner_driver_id": 923,
		"pole_winner_speed": 135.164,
		"pole_winner_laptime": null,
		"number_of_lead_changes": 9,
		"number_of_leaders": 7,
		"number_of_cautions": 7,
		"number_of_caution_laps": 34,
		"average_speed": 108.504,
		"total_race_time": "02:56:06",
		"race_purse": 5386439.0,
		"race_comments": "Kyle Busch won the 5-hour ENERGY 301, his 32nd career NASCAR Sprint Cup Series victory, and second at New Hampshire Motor Speedway. Prior to the start of the race, no cars dropped to the rear of the field.",
		"attendance": 0,
		"radio_broadcaster": "PRN",
		"television_broadcaster": "NBCSN",
		"master_race_id": 1683
	},
	{
		"race_id": 4411,
		"series_id": 1,
		"race_season": 2015,
		"race_name": "Sylvania 300",
		"race_type_id": 1,
		"restrictor_plate": false,
		"track_id": 138,
		"track_name": "New Hampshire Motor Speedway",
		"date_scheduled": "2015-09-27T14:00:00",
		"race_date": "2015-09-27T14:00:00",
		"qualifying_date": "2015-09-25T00:00:00",
		"scheduled_distance": 317.4,
		"actual_distance": 317.4,
		"scheduled_laps": 300,
		"actual_laps": 300,
		"number_of_cars_in_field": 43,
		"pole_winner_driver_id": 923,
		"pole_winner_speed": 137.98,
		"pole_winner_laptime": null,
		"number_of_lead_changes": 16,
		"number_of_leaders": 7,
		"number_of_cautions": 9,
		"number_of_caution_laps": 41,
		"average_speed": 106.48,
		"total_race_time": "02:58:51",
		"race_purse": 5386439.0,
		"race_comments": "Matt Kenseth won the SYLVANIA 300, his 36th career NASCAR Sprint Cup Series victory. Prior to the start of the race, the following cars dropped to the rear of the field for the reasons indicated: No. 32 (Rear Gear Change).",
		"attendance": 0,
		"radio_broadcaster": "PRN",
		"television_broadcaster": "NBCSN",
		"master_race_id": 1814
	},
	{
		"race_id": 4405,
		"series_id": 1,
		"race_season": 2015,
		"race_name": "Cheez-It 355",
		"race_type_id": 1,
		"restrictor_plate": false,
		"track_id": 157,
		"track_name": "Watkins Glen International",
		"date_scheduled": "2015-08-09T14:00:00",
		"race_date": "2015-08-09T14:00:00",
		"qualifying_date": "2015-08-08T00:00:00",
		"scheduled_distance": 220.5,
		"actual_distance": 220.5,
		"scheduled_laps": 90,
		"actual_laps": 90,
		"number_of_cars_in_field": 43,
		"pole_winner_driver_id": 3774,
		"pole_winner_speed": 127.839,
		"pole_winner_laptime": null,
		"number_of_lead_changes": 8,
		"number_of_leaders": 8,
		"number_of_cautions": 5,
		"number_of_caution_laps": 16,
		"average_speed": 91.42,
		"total_race_time": "02:24:43",
		"race_purse": 4960524.0,
		"race_comments": "Joey Logano won the CHEEZ-It 355 at The Glen, his 10th career NASCAR Sprint Cup Series victory. Prior to the start of the race, no cars dropped to the rear of the field.",
		"attendance": 0,
		"radio_broadcaster": "MRN",
		"television_broadcaster": "NBCSN",
		"master_race_id": 1482
	},
	{
		"race_id": 4393,
		"series_id": 1,
		"race_season": 2015,
		"race_name": "Sprint Showdown",
		"race_type_id": 2,
		"restrictor_plate": false,
		"track_id": 162,
		"track_name": "Charlotte Motor Speedway",
		"date_scheduled": "2015-05-15T19:00:00",
		"race_date": "2015-05-15T19:00:00",
		"qualifying_date": "2015-05-15T00:00:00",
		"scheduled_distance": 60.0,
		"actual_distance": 60.0,
		"scheduled_laps": 40,
		"actual_laps": 40,
		"number_of_cars_in_field": 29,
		"pole_winner_driver_id": 2225,
		"pole_winner_speed": 189.673,
		"pole_winner_laptime": null,
		"number_of_lead_changes": 4,
		"number_of_leaders": 4,
		"number_of_cautions": 2,
		"number_of_caution_laps": 2,
		"average_speed": 102.37,
		"total_race_time": "00:35:10",
		"race_purse": 0.0,
		"race_comments": "Greg Biffle and Clint Bowyer won the two segments in the Sprint Showdown.",
		"attendance": 0,
		"radio_broadcaster": "MRN",
		"television_broadcaster": "FS1",
		"master_race_id": 3690
	},
	{
		"race_id": 4394,
		"series_id": 1,
		"race_season": 2015,
		"race_name": "NASCAR Sprint All-Star Race",
		"race_type_id": 2,
		"restrictor_plate": false,
		"track_id": 162,
		"track_name": "Charlotte Motor Speedway",
		"date_scheduled": "2015-05-16T19:00:00",
		"race_date": "2015-05-16T19:00:00",
		"qualifying_date": "2015-05-16T00:00:00",
		"scheduled_distance": 135.0,
		"actual_distance": 165.0,
		"scheduled_laps": 110,
		"actual_laps": 110,
		"number_of_cars_in_field": 20,
		"pole_winner_driver_id": 1361,
		"pole_winner_speed": 145.648,
		"pole_winner_laptime": null,
		"number_of_lead_changes": 7,
		"number_of_leaders": 4,
		"number_of_cautions": 4,
		"number_of_caution_laps": 4,
		"average_speed": 106.452,
		"total_race_time": "01:33:00",
		"race_purse": 0.0,
		"race_comments": "Denny Hamlin won the NASCAR Sprint All-Star Race, his first win in the annual non-points race. Prior to the start of the race, the following car dropped to the rear of the field for the reason indicated: No. 10 (engine change).",
		"attendance": 0,
		"radio_broadcaster": "MRN",
		"television_broadcaster": "FS1",
		"master_race_id": 3670
	},
	{
		"race_id": 4395,
		"series_id": 1,
		"race_season": 2015,
		"race_name": "Coca-Cola 600",
		"race_type_id": 1,
		"restrictor_plate": false,
		"track_id": 162,
		"track_name": "Charlotte Motor Speedway",
		"date_scheduled": "2015-05-24T18:00:00",
		"race_date": "2015-05-24T18:00:00",
		"qualifying_date": "2015-05-21T00:00:00",
		"scheduled_distance": 600.0,
		"actual_distance": 600.0,
		"scheduled_laps": 400,
		"actual_laps": 400,
		"number_of_cars_in_field": 43,
		"pole_winner_driver_id": 1810,
		"pole_winner_speed": 194.252,
		"pole_winner_laptime": null,
		"number_of_lead_changes": 22,
		"number_of_leaders": 9,
		"number_of_cautions": 8,
		"number_of_caution_laps": 39,
		"average_speed": 147.803,
		"total_race_time": "04:03:34",
		"race_purse": 6660588.0,
		"race_comments": "Carl Edwards won the Coca-Cola 600, his 24th career NASCAR Sprint Cup Series victory. ",
		"attendance": 0,
		"radio_broadcaster": "PRN",
		"television_broadcaster": "FOX",
		"master_race_id": 447
	},
	{
		"race_id": 4414,
		"series_id": 1,
		"race_season": 2015,
		"race_name": "Bank of America 500",
		"race_type_id": 1,
		"restrictor_plate": false,
		"track_id": 162,
		"track_name": "Charlotte Motor Speedway",
		"date_scheduled": "2015-10-10T19:00:00",
		"race_date": "2015-10-11T12:30:00",
		"qualifying_date": "2015-10-08T00:00:00",
		"scheduled_distance": 501.0,
		"actual_distance": 501.0,
		"scheduled_laps": 334,
		"actual_laps": 334,
		"number_of_cars_in_field": 43,
		"pole_winner_driver_id": 1810,
		"pole_winner_speed": 194.532,
		"pole_winner_laptime": null,
		"number_of_lead_changes": 14,
		"number_of_leaders": 10,
		"number_of_cautions": 9,
		"number_of_caution_laps": 44,
		"average_speed": 139.76,
		"total_race_time": "03:35:05",
		"race_purse": 5306331.0,
		"race_comments": "Joey Logano won the Bank of America 500, his 12th career NASCAR Sprint Cup Series victory.",
		"attendance": 0,
		"radio_broadcaster": "PRN",
		"television_broadcaster": "NBCSN",
		"master_race_id": 468
	},
	{
		"race_id": 4397,
		"series_id": 1,
		"race_season": 2015,
		"race_name": "Axalta 'We Paint Winners' 400",
		"race_type_id": 1,
		"restrictor_plate": false,
		"track_id": 198,
		"track_name": "Pocono Raceway",
		"date_scheduled": "2015-06-07T13:00:00",
		"race_date": "2015-06-07T13:00:00",
		"qualifying_date": "2015-06-05T00:00:00",
		"scheduled_distance": 400.0,
		"actual_distance": 400.0,
		"scheduled_laps": 160,
		"actual_laps": 160,
		"number_of_cars_in_field": 43,
		"pole_winner_driver_id": 453,
		"pole_winner_speed": 177.599,
		"pole_winner_laptime": null,
		"number_of_lead_changes": 12,
		"number_of_leaders": 6,
		"number_of_cautions": 8,
		"number_of_caution_laps": 31,
		"average_speed": 134.266,
		"total_race_time": "02:58:45",
		"race_purse": 5084726.0,
		"race_comments": "Martin Truex Jr. won the Axalta 'We Paint Winners' 400, his third career NASCAR Sprint Series victory. Prior to the start of the race, the following car dropped to the rear of the field for the reason indicated: No. 22 (changing rear gear).",
		"attendance": 0,
		"radio_broadcaster": "MRN",
		"television_broadcaster": "FS1",
		"master_race_id": 1358
	},
	{
		"race_id": 4404,
		"series_id": 1,
		"race_season": 2015,
		"race_name": "Windows 10 400",
		"race_type_id": 1,
		"restrictor_plate": false,
		"track_id": 198,
		"track_name": "Pocono Raceway",
		"date_scheduled": "2015-08-02T13:30:00",
		"race_date": "2015-08-02T13:30:00",
		"qualifying_date": "2015-07-31T00:00:00",
		"scheduled_distance": 400.0,
		"actual_distance": 400.0,
		"scheduled_laps": 160,
		"actual_laps": 160,
		"number_of_cars_in_field": 43,
		"pole_winner_driver_id": 454,
		"pole_winner_speed": 178.416,
		"pole_winner_laptime": null,
		"number_of_lead_changes": 18,
		"number_of_leaders": 13,
		"number_of_cautions": 8,
		"number_of_caution_laps": 32,
		"average_speed": 132.159,
		"total_race_time": "03:01:36",
		"race_purse": 5084726.0,
		"race_comments": "Matt Kenseth won the Windows 10 400, his 33rd career NASCAR Sprint Cup Series victory. Prior to the start of the race, the following cars dropped to the rear of the field for the reasons indicated: No. 26 (backup car); No. 31 (rear gear).",
		"attendance": 0,
		"radio_broadcaster": "MRN",
		"television_broadcaster": "NBCSN",
		"master_race_id": 1122
	}
]
